README.rst
setup.py
zar/LICENSE
zar/__init__.py
zar/__main__.py
zar/bck_filestore.sh
zar/check_4_seq.sh
zar/pg_db_active
zar/pg_db_reassign_owner
zar/zar_bck
zar/zar_cptbl
zar/zar_purge
zar/zar_rest
zar/zar_upd
zar/zarrc
zar.egg-info/PKG-INFO
zar.egg-info/SOURCES.txt
zar.egg-info/dependency_links.txt
zar.egg-info/not-zip-safe
zar.egg-info/top_level.txt
zar/docs/Makefile
zar/docs/conf.py
zar/docs/index.rst
zar/docs/logozero_180x46.png
zar/docs/readthedocs.yml
zar/docs/requirements.txt
zar/docs/rtd_changelog.rst
zar/docs/rtd_credits.rst
zar/docs/rtd_description.rst
zar/docs/rtd_features.rst
zar/docs/rtd_getting_started.rst
zar/docs/rtd_usage.rst
zar/egg-info/CHANGELOG.rst
zar/egg-info/CONTRIBUTORS.txt
zar/egg-info/DESCRIPTION.rst
zar/egg-info/FEATURES.rst
zar/egg-info/INSTALLATION.rst
zar/egg-info/USAGE.rst
zar/scripts/__init__.py
zar/scripts/main.py